banker/__init__.py
banker/accounts.py
banker/agreements.py
banker/client.py
banker/enums.py
banker/institutions.py
banker/requisitions.py
banker-0.1.0.dist-info/WHEEL
banker-0.1.0.dist-info/METADATA
banker-0.1.0.dist-info/RECORD
